README
nporttool
setup.py
nport/__init__.py
nport/citi.py
nport/deemb.py
nport/nport.py
nport/parameter.py
nport/tline.py
nport/tool.py
nport/touchstone.py
nport/twonport.py
nport/version.py
nport.egg-info/PKG-INFO
nport.egg-info/SOURCES.txt
nport.egg-info/dependency_links.txt
nport.egg-info/top_level.txt