Metadata-Version: 1.1
Name: nport
Version: 0.1
Summary: Python package for handling n-port data
Home-page: https://github.com/bmachiel/python-nport
Author: Brecht Machiels
Author-email: brecht.machiels@esat.kuleuven.be
License: GPL
Keywords: two-port 2n-port s-parameters touchstone citi deembedding
Platform: UNKNOWN
Requires: numpy
Requires: scipy
